CHANGES
MANIFEST.in
README
setup.py
whatsnew/__init__.py
whatsnew/__init__.pyc
whatsnew/admin.py
whatsnew/admin.pyc
whatsnew/fields.py
whatsnew/fields.pyc
whatsnew/models.py
whatsnew/models.pyc
whatsnew/urls.py
whatsnew/urls.pyc
whatsnew/util.py
whatsnew/util.pyc
whatsnew/views.py
whatsnew/views.pyc
whatsnew.egg-info/PKG-INFO
whatsnew.egg-info/SOURCES.txt
whatsnew.egg-info/dependency_links.txt
whatsnew.egg-info/top_level.txt
whatsnew/migrations/0001_initial.py
whatsnew/migrations/0001_initial.pyc
whatsnew/migrations/0002_auto__add_field_whatsnew_released.py
whatsnew/migrations/0002_auto__add_field_whatsnew_released.pyc
whatsnew/migrations/0003_auto__chg_field_whatsnew_version.py
whatsnew/migrations/0003_auto__chg_field_whatsnew_version.pyc
whatsnew/migrations/0004_auto__del_field_whatsnew_released__add_field_whatsnew_enabled__chg_fie.py
whatsnew/migrations/0004_auto__del_field_whatsnew_released__add_field_whatsnew_enabled__chg_fie.pyc
whatsnew/migrations/0005_auto__add_field_whatsnew_expire.py
whatsnew/migrations/0005_auto__add_field_whatsnew_expire.pyc
whatsnew/migrations/__init__.py
whatsnew/migrations/__init__.pyc
whatsnew/static/whatsnew/js/jquery.bpopup.min.js
whatsnew/templates/admin/whatsnew/change_form_whatsnew.html
whatsnew/templates/whatsnew/test.html
whatsnew/templates/whatsnew/whatsnew.html
whatsnew/templatetags/__init__.py
whatsnew/templatetags/__init__.pyc
whatsnew/templatetags/whatsnew.py
whatsnew/templatetags/whatsnew.pyc