Metadata-Version: 1.1
Name: whatsnew
Version: 0.2
Summary: Simple application to manage `what's new` screen.
Home-page: https://github.com/saxix/django-whatsnew
Author: sax
Author-email: sax@os4d.org
License: BSD
Platform: linux
Classifier: Environment :: Web Environment
Classifier: Framework :: Django
Classifier: Operating System :: OS Independent
Classifier: Programming Language :: Python :: 2.7
Classifier: Intended Audience :: Developers
